geetools/__init__.py
geetools/accessors.py
geetools/ee_array.py
geetools/ee_asset.py
geetools/ee_authenticate.py
geetools/ee_computed_object.py
geetools/ee_date.py
geetools/ee_date_range.py
geetools/ee_dictionary.py
geetools/ee_export.py
geetools/ee_feature.py
geetools/ee_feature_collection.py
geetools/ee_filter.py
geetools/ee_geometry.py
geetools/ee_image.py
geetools/ee_image_collection.py
geetools/ee_initialize.py
geetools/ee_join.py
geetools/ee_list.py
geetools/ee_number.py
geetools/ee_profiler.py
geetools/ee_string.py
geetools/utils.py
geetools-1.18.1.dist-info/METADATA
geetools-1.18.1.dist-info/WHEEL
geetools-1.18.1.dist-info/licenses/AUTHORS.rst
geetools-1.18.1.dist-info/licenses/LICENSE
geetools-1.18.1.dist-info/RECORD
