Metadata-Version: 2.4
Name: geetools
Version: 1.18.1
Summary: A collection of tools to work with Google Earth Engine Python API
Project-URL: Homepage, https://github.com/gee-community/geetools
Author-email: "Rodrigo E. Principe" <fitoprincipe82@gmail.com>
License: MIT
License-File: AUTHORS.rst
License-File: LICENSE
Keywords: earthengine,geospatial,google-earth-engine,python,remote-sensing
Classifier: Development Status :: 5 - Production/Stable
Classifier: Intended Audience :: Developers
Classifier: License :: OSI Approved :: MIT License
Classifier: Programming Language :: Python :: 3.10
Classifier: Programming Language :: Python :: 3.11
Classifier: Programming Language :: Python :: 3.12
Classifier: Programming Language :: Python :: 3.13
Classifier: Topic :: Software Development :: Build Tools
Requires-Python: >=3.10
Requires-Dist: anyascii
Requires-Dist: deprecated
Requires-Dist: earthengine-api>=1.6.12
Requires-Dist: ee-extra>=2025.7.2
Requires-Dist: geopandas
Requires-Dist: matplotlib
Requires-Dist: pandas
Requires-Dist: requests
Requires-Dist: xee>=0.0.11
Requires-Dist: yamlable
Provides-Extra: dev
Requires-Dist: commitizen; extra == 'dev'
Requires-Dist: nox; extra == 'dev'
Requires-Dist: pre-commit; extra == 'dev'
Provides-Extra: doc
Requires-Dist: httplib2; extra == 'doc'
Requires-Dist: ipykernel; extra == 'doc'
Requires-Dist: jupyter-sphinx; extra == 'doc'
Requires-Dist: myst-nb; extra == 'doc'
Requires-Dist: pydata-sphinx-theme; extra == 'doc'
Requires-Dist: pytest-gee>=0.3.7; extra == 'doc'
Requires-Dist: sphinx-autoapi; extra == 'doc'
Requires-Dist: sphinx-copybutton; extra == 'doc'
Requires-Dist: sphinx-design; extra == 'doc'
Requires-Dist: sphinx-icon; extra == 'doc'
Requires-Dist: sphinx-last-updated-by-git; extra == 'doc'
Requires-Dist: sphinx>=6.2.1; extra == 'doc'
Provides-Extra: test
Requires-Dist: httplib2; extra == 'test'
Requires-Dist: jsonschema; extra == 'test'
Requires-Dist: pillow; extra == 'test'
Requires-Dist: pytest; extra == 'test'
Requires-Dist: pytest-cov; extra == 'test'
Requires-Dist: pytest-deadfixtures; extra == 'test'
Requires-Dist: pytest-gee>=0.6.0; extra == 'test'
Requires-Dist: pytest-regressions; extra == 'test'
